tinybeans_sync/__init__.py
tinybeans_sync/api.py
tinybeans_sync/auth.py
tinybeans_sync/cli.py
tinybeans_sync/downloader.py
tinybeans_sync/history.py
tinybeans_sync-0.2.dist-info/METADATA
tinybeans_sync-0.2.dist-info/WHEEL
tinybeans_sync-0.2.dist-info/entry_points.txt
tinybeans_sync-0.2.dist-info/licenses/LICENSE
tinybeans_sync-0.2.dist-info/RECORD
