Metadata-Version: 2.4
Name: tinybeans-sync
Version: 0.2
Summary: Download original quality images from Tinybeans photo journals
Project-URL: Repository, https://github.com/brege/tinybeans-sync
Author: Wyatt Brege
License-Expression: GPL-3.0-or-later
License-File: LICENSE
Classifier: Development Status :: 4 - Beta
Classifier: Environment :: Console
Classifier: License :: OSI Approved :: GNU General Public License v3 or later (GPLv3+)
Classifier: Programming Language :: Python :: 3
Classifier: Programming Language :: Python :: 3.8
Classifier: Programming Language :: Python :: 3.9
Classifier: Programming Language :: Python :: 3.10
Classifier: Programming Language :: Python :: 3.11
Classifier: Programming Language :: Python :: 3.12
Classifier: Topic :: Multimedia :: Graphics
Requires-Python: >=3.8
Requires-Dist: beautifulsoup4>=4.11.0
Requires-Dist: click-help-colors>=0.9
Requires-Dist: click>=8.3.1
Requires-Dist: pyyaml>=6.0
Requires-Dist: requests>=2.28.0
